ittybit/__init__.py
ittybit/automations/__init__.py
ittybit/automations/client.py
ittybit/automations/raw_client.py
ittybit/automations/requests/__init__.py
ittybit/automations/requests/automations_create_request_trigger.py
ittybit/automations/requests/automations_create_request_workflow_item.py
ittybit/automations/requests/automations_create_request_workflow_item_next_item.py
ittybit/automations/requests/automations_create_response.py
ittybit/automations/requests/automations_create_response_trigger.py
ittybit/automations/requests/automations_create_response_workflow_item.py
ittybit/automations/requests/automations_create_response_workflow_item_conditions.py
ittybit/automations/requests/automations_create_response_workflow_item_conditions_conditions_item.py
ittybit/automations/requests/automations_create_response_workflow_item_conditions_next_item.py
ittybit/automations/requests/automations_create_response_workflow_item_ref.py
ittybit/automations/requests/automations_create_response_workflow_item_ref_next_item.py
ittybit/automations/requests/automations_delete_response.py
ittybit/automations/requests/automations_get_response.py
ittybit/automations/requests/automations_get_response_trigger.py
ittybit/automations/requests/automations_get_response_workflow_item.py
ittybit/automations/requests/automations_get_response_workflow_item_conditions.py
ittybit/automations/requests/automations_get_response_workflow_item_conditions_conditions_item.py
ittybit/automations/requests/automations_get_response_workflow_item_conditions_next_item.py
ittybit/automations/requests/automations_get_response_workflow_item_ref.py
ittybit/automations/requests/automations_get_response_workflow_item_ref_next_item.py
ittybit/automations/requests/automations_list_response_item.py
ittybit/automations/requests/automations_list_response_item_trigger.py
ittybit/automations/requests/automations_list_response_item_workflow_item.py
ittybit-1.0.0.dist-info/LICENSE
ittybit-1.0.0.dist-info/METADATA
ittybit-1.0.0.dist-info/WHEEL
ittybit-1.0.0.dist-info/RECORD
